ezcf/__init__.py
ezcf/_base.py
ezcf/api.py
ezcf/type_ini.py
ezcf/type_json.py
ezcf/type_xml.py
ezcf/type_yaml.py
ezcf-0.2.1.dist-info/DESCRIPTION.rst
ezcf-0.2.1.dist-info/METADATA
ezcf-0.2.1.dist-info/RECORD
ezcf-0.2.1.dist-info/WHEEL
ezcf-0.2.1.dist-info/metadata.json
ezcf-0.2.1.dist-info/top_level.txt
