Metadata-Version: 2.0
Name: ezcf
Version: 0.2.1
Summary: Import JSON/YAML/INI/XML like .py files
Home-page: http://github.com/laike9m/ezcf/
Author: laike9m
Author-email: laike9m@gmail.com
License: MIT
Keywords: config,import,JSON,YAML,INI,XML
Platform: UNKNOWN
Classifier: Development Status :: 3 - Alpha
Classifier: Intended Audience :: Developers
Classifier: Natural Language :: English
Classifier: License :: OSI Approved :: MIT License
Classifier: Operating System :: OS Independent
Classifier: Programming Language :: Python
Classifier: Programming Language :: Python :: 2
Classifier: Programming Language :: Python :: 2.6
Classifier: Programming Language :: Python :: 2.7
Classifier: Programming Language :: Python :: 3
Classifier: Programming Language :: Python :: 3.3
Classifier: Programming Language :: Python :: 3.4
Classifier: Programming Language :: Python :: 3.5
Classifier: Topic :: Software Development :: Libraries :: Python Modules
Classifier: Programming Language :: Python :: Implementation :: PyPy
Classifier: Programming Language :: Python :: Implementation :: CPython
Requires-Dist: configobj (==5.0.6)
Requires-Dist: pyyaml (==3.11)
Requires-Dist: xmltodict (==0.9.2)
Provides-Extra: coveralls
Requires-Dist: coveralls; extra == 'coveralls'
